{
  "aspectWidth": 4,
  "aspectHeight": 3,
  "frames": [
    {
      "frameId": "frame6477",
      "title": "Title",
      "timeoutMs": 0,
      "timeoutEnable": false,
      "transitionDurationMs": 1000,
      "showInFrameList": true,
      "showFrameNumber": true,
      "layerProperties": {
        "layer2": {
          "link": false,
          "referenceElementId": "rect3001-8",
          "outlineElementId": "rect3001-8",
          "outlineElementAuto": true,
          "transitionTimingFunction": "linear",
          "transitionRelativeZoom": 0,
          "transitionPathId": ""
        },
        "layer3": {
          "link": false,
          "referenceElementId": "",
          "outlineElementId": "image19417",
          "outlineElementAuto": true,
          "transitionTimingFunction": "linear",
          "transitionRelativeZoom": 0,
          "transitionPathId": ""
        },
        "layer1": {
          "link": false,
          "referenceElementId": "image19417",
          "outlineElementId": "image19417",
          "outlineElementAuto": true,
          "transitionTimingFunction": "linear",
          "transitionRelativeZoom": 0,
          "transitionPathId": ""
        },
        "__sozi_auto__": {
          "link": false,
          "referenceElementId": "",
          "outlineElementId": "image19417",
          "outlineElementAuto": true,
          "transitionTimingFunction": "linear",
          "transitionRelativeZoom": 0,
          "transitionPathId": ""
        }
      },
      "cameraStates": {
        "layer2": {
          "cx": 1785.5036080860511,
          "cy": 8648.459552366347,
          "width": 2848.422463284651,
          "height": 2137.0934075679825,
          "opacity": 1,
          "angle": 0,
          "clipped": false,
          "clipXOffset": 0,
          "clipYOffset": 0,
          "clipWidthFactor": 1,
          "clipHeightFactor": 1
        },
        "layer3": {
          "cx": 1494.0660496765543,
          "cy": 5663.480752144019,
          "width": 3140.385765771327,
          "height": 2356.1454818437,
          "opacity": 1,
          "angle": 0,
          "clipped": false,
          "clipXOffset": 0,
          "clipYOffset": 0,
          "clipWidthFactor": 1,
          "clipHeightFactor": 1
        },
        "layer1": {
          "cx": 1494.0660496765543,
          "cy": 5663.480752144019,
          "width": 3140.3857657713284,
          "height": 2356.1454818437014,
          "opacity": 1,
          "angle": 0,
          "clipped": false,
          "clipXOffset": 0,
          "clipYOffset": 0,
          "clipWidthFactor": 1,
          "clipHeightFactor": 1
        },
        "__sozi_auto__": {
          "cx": 1494.0660496765543,
          "cy": 5663.480752144019,
          "width": 3140.385765771327,
          "height": 2356.1454818437,
          "opacity": 1,
          "angle": 0,
          "clipped": false,
          "clipXOffset": 0,
          "clipYOffset": 0,
          "clipWidthFactor": 1,
          "clipHeightFactor": 1
        }
      },
      "cameraOffsets": {
        "layer2": {
          "deltaX": 23.203925468863645,
          "deltaY": 9.413653928846543,
          "widthFactor": 0.941494893264936,
          "heightFactor": 0.940252912629432,
          "deltaAngle": 0
        },
        "layer1": {
          "deltaX": -947.7335108703207,
          "deltaY": -497.1027439497311,
          "widthFactor": 3.205341670398134,
          "heightFactor": 2.142640224004954,
          "deltaAngle": 0
        }
      }
    },
    {
      "frameId": "frame2346",
      "title": "What is SIAnPy?",
      "timeoutMs": 0,
      "timeoutEnable": false,
      "transitionDurationMs": 1000,
      "showInFrameList": true,
      "showFrameNumber": true,
      "layerProperties": {
        "layer2": {
          "link": true,
          "referenceElementId": "",
          "outlineElementId": "",
          "outlineElementAuto": true,
          "transitionTimingFunction": "linear",
          "transitionRelativeZoom": 0,
          "transitionPathId": ""
        },
        "layer3": {
          "link": false,
          "referenceElementId": "",
          "outlineElementId": "text3790-7",
          "outlineElementAuto": true,
          "transitionTimingFunction": "linear",
          "transitionRelativeZoom": 0,
          "transitionPathId": ""
        },
        "layer1": {
          "link": false,
          "referenceElementId": "text3790-7",
          "outlineElementId": "text3790-7",
          "outlineElementAuto": true,
          "transitionTimingFunction": "linear",
          "transitionRelativeZoom": 0,
          "transitionPathId": ""
        },
        "__sozi_auto__": {
          "link": false,
          "referenceElementId": "",
          "outlineElementId": "text3790-7",
          "outlineElementAuto": true,
          "transitionTimingFunction": "linear",
          "transitionRelativeZoom": 0,
          "transitionPathId": ""
        }
      },
      "cameraStates": {
        "layer2": {
          "cx": 1785.5036080860511,
          "cy": 8648.459552366347,
          "width": 2848.422463284651,
          "height": 2137.0934075679825,
          "opacity": 1,
          "angle": 0,
          "clipped": false,
          "clipXOffset": 0,
          "clipYOffset": 0,
          "clipWidthFactor": 1,
          "clipHeightFactor": 1
        },
        "layer3": {
          "cx": 1373.8565516696833,
          "cy": 3886.325756279268,
          "width": 2994.1735972597894,
          "height": 2243.9480779463815,
          "opacity": 1,
          "angle": 0,
          "clipped": false,
          "clipXOffset": 0,
          "clipYOffset": 0,
          "clipWidthFactor": 1,
          "clipHeightFactor": 1
        },
        "layer1": {
          "cx": 1366.7620772979437,
          "cy": 3889.2975121061895,
          "width": 3007.9315360558357,
          "height": 2254.2588028643177,
          "opacity": 1,
          "angle": 0,
          "clipped": false,
          "clipXOffset": 0,
          "clipYOffset": 0,
          "clipWidthFactor": 1,
          "clipHeightFactor": 1
        },
        "__sozi_auto__": {
          "cx": 1373.8565516696833,
          "cy": 3886.325756279268,
          "width": 2994.1735972597894,
          "height": 2243.9480779463815,
          "opacity": 1,
          "angle": 0,
          "clipped": false,
          "clipXOffset": 0,
          "clipYOffset": 0,
          "clipWidthFactor": 1,
          "clipHeightFactor": 1
        }
      },
      "cameraOffsets": {
        "layer1": {
          "deltaX": 59.86315151669373,
          "deltaY": -248.49448008131048,
          "widthFactor": 1.147843792066414,
          "heightFactor": 2.9779244295286937,
          "deltaAngle": 0
        }
      }
    },
    {
      "frameId": "frame8531",
      "title": "SIAnPy",
      "timeoutMs": 0,
      "timeoutEnable": false,
      "transitionDurationMs": 1000,
      "showInFrameList": true,
      "showFrameNumber": true,
      "layerProperties": {
        "layer2": {
          "link": true,
          "referenceElementId": "",
          "outlineElementId": "",
          "outlineElementAuto": true,
          "transitionTimingFunction": "linear",
          "transitionRelativeZoom": 0,
          "transitionPathId": ""
        },
        "layer3": {
          "link": false,
          "referenceElementId": "",
          "outlineElementId": "text3790-7",
          "outlineElementAuto": true,
          "transitionTimingFunction": "linear",
          "transitionRelativeZoom": 0,
          "transitionPathId": ""
        },
        "layer1": {
          "link": false,
          "referenceElementId": "text3790-7",
          "outlineElementId": "text3790-7",
          "outlineElementAuto": true,
          "transitionTimingFunction": "linear",
          "transitionRelativeZoom": 0,
          "transitionPathId": ""
        },
        "__sozi_auto__": {
          "link": false,
          "referenceElementId": "",
          "outlineElementId": "text3790-7",
          "outlineElementAuto": true,
          "transitionTimingFunction": "linear",
          "transitionRelativeZoom": 0,
          "transitionPathId": ""
        }
      },
      "cameraStates": {
        "layer2": {
          "cx": 1785.5036080860511,
          "cy": 8648.459552366347,
          "width": 2848.422463284651,
          "height": 2137.0934075679825,
          "opacity": 1,
          "angle": 0,
          "clipped": false,
          "clipXOffset": 0,
          "clipYOffset": 0,
          "clipWidthFactor": 1,
          "clipHeightFactor": 1
        },
        "layer3": {
          "cx": 1503.8624278817224,
          "cy": 3713.458880971696,
          "width": 3143.8103958321485,
          "height": 2356.145481843702,
          "opacity": 1,
          "angle": 0,
          "clipped": false,
          "clipXOffset": 0,
          "clipYOffset": 0,
          "clipWidthFactor": 1,
          "clipHeightFactor": 1
        },
        "layer1": {
          "cx": 1496.8505127745734,
          "cy": 3716.872374952002,
          "width": 3158.3281128586273,
          "height": 2367.0258623602786,
          "opacity": 1,
          "angle": 0,
          "clipped": false,
          "clipXOffset": 0,
          "clipYOffset": 0,
          "clipWidthFactor": 1,
          "clipHeightFactor": 1
        },
        "__sozi_auto__": {
          "cx": 1503.8624278817224,
          "cy": 3713.458880971696,
          "width": 3143.8103958321485,
          "height": 2356.145481843702,
          "opacity": 1,
          "angle": 0,
          "clipped": false,
          "clipXOffset": 0,
          "clipYOffset": 0,
          "clipWidthFactor": 1,
          "clipHeightFactor": 1
        }
      },
      "cameraOffsets": {
        "layer1": {
          "deltaX": 189.95158699332342,
          "deltaY": -420.9196172354982,
          "widthFactor": 1.2052359816697347,
          "heightFactor": 3.1268921438356965,
          "deltaAngle": 0
        }
      }
    },
    {
      "frameId": "frame5600",
      "title": "What is a SI?",
      "timeoutMs": 0,
      "timeoutEnable": false,
      "transitionDurationMs": 1000,
      "showInFrameList": true,
      "showFrameNumber": true,
      "layerProperties": {
        "layer2": {
          "link": true,
          "referenceElementId": "",
          "outlineElementId": "",
          "outlineElementAuto": true,
          "transitionTimingFunction": "linear",
          "transitionRelativeZoom": 0,
          "transitionPathId": ""
        },
        "layer3": {
          "link": false,
          "referenceElementId": "",
          "outlineElementId": "text19501",
          "outlineElementAuto": true,
          "transitionTimingFunction": "linear",
          "transitionRelativeZoom": 0,
          "transitionPathId": ""
        },
        "layer1": {
          "link": false,
          "referenceElementId": "text19501",
          "outlineElementId": "text19501",
          "outlineElementAuto": true,
          "transitionTimingFunction": "linear",
          "transitionRelativeZoom": 0,
          "transitionPathId": ""
        },
        "__sozi_auto__": {
          "link": false,
          "referenceElementId": "",
          "outlineElementId": "text19501",
          "outlineElementAuto": true,
          "transitionTimingFunction": "linear",
          "transitionRelativeZoom": 0,
          "transitionPathId": ""
        }
      },
      "cameraStates": {
        "layer2": {
          "cx": 1785.5036080860511,
          "cy": 8648.459552366347,
          "width": 2848.422463284651,
          "height": 2137.0934075679825,
          "opacity": 1,
          "angle": 0,
          "clipped": false,
          "clipXOffset": 0,
          "clipYOffset": 0,
          "clipWidthFactor": 1,
          "clipHeightFactor": 1
        },
        "layer3": {
          "cx": 2506.74393811847,
          "cy": 2411.967056916507,
          "width": 727.406828445406,
          "height": 545.1589302510232,
          "opacity": 1,
          "angle": 0,
          "clipped": false,
          "clipXOffset": 0,
          "clipYOffset": 0,
          "clipWidthFactor": 1,
          "clipHeightFactor": 1
        },
        "layer1": {
          "cx": 2538.5369310746883,
          "cy": 2414.255227644585,
          "width": 754.8275623828899,
          "height": 565.7095456638652,
          "opacity": 1,
          "angle": 0,
          "clipped": false,
          "clipXOffset": 0,
          "clipYOffset": 0,
          "clipWidthFactor": 1,
          "clipHeightFactor": 1
        },
        "__sozi_auto__": {
          "cx": 2506.74393811847,
          "cy": 2411.967056916507,
          "width": 727.406828445406,
          "height": 545.1589302510232,
          "opacity": 1,
          "angle": 0,
          "clipped": false,
          "clipXOffset": 0,
          "clipYOffset": 0,
          "clipWidthFactor": 1,
          "clipHeightFactor": 1
        }
      },
      "cameraOffsets": {
        "layer1": {
          "deltaX": -5.948420487811745,
          "deltaY": -1.2433075116650798,
          "widthFactor": 0.990336957146383,
          "heightFactor": 3.043723481574449,
          "deltaAngle": 0
        }
      }
    },
    {
      "frameId": "frame6036",
      "title": "A SI",
      "timeoutMs": 0,
      "timeoutEnable": false,
      "transitionDurationMs": 1000,
      "showInFrameList": true,
      "showFrameNumber": true,
      "layerProperties": {
        "layer2": {
          "link": true,
          "referenceElementId": "",
          "outlineElementId": "",
          "outlineElementAuto": true,
          "transitionTimingFunction": "linear",
          "transitionRelativeZoom": 0,
          "transitionPathId": ""
        },
        "layer3": {
          "link": false,
          "referenceElementId": "",
          "outlineElementId": "path4316",
          "outlineElementAuto": true,
          "transitionTimingFunction": "linear",
          "transitionRelativeZoom": 0,
          "transitionPathId": ""
        },
        "layer1": {
          "link": false,
          "referenceElementId": "path4316",
          "outlineElementId": "path4316",
          "outlineElementAuto": true,
          "transitionTimingFunction": "linear",
          "transitionRelativeZoom": 0,
          "transitionPathId": ""
        },
        "__sozi_auto__": {
          "link": false,
          "referenceElementId": "",
          "outlineElementId": "path4316",
          "outlineElementAuto": true,
          "transitionTimingFunction": "linear",
          "transitionRelativeZoom": 0,
          "transitionPathId": ""
        }
      },
      "cameraStates": {
        "layer2": {
          "cx": 1785.5036080860511,
          "cy": 8648.459552366347,
          "width": 2848.422463284651,
          "height": 2137.0934075679825,
          "opacity": 1,
          "angle": 0,
          "clipped": false,
          "clipXOffset": 0,
          "clipYOffset": 0,
          "clipWidthFactor": 1,
          "clipHeightFactor": 1
        },
        "layer3": {
          "cx": 3625.3577262240406,
          "cy": 1278.0782379095826,
          "width": 3817.1585257061006,
          "height": 2863.909559090291,
          "opacity": 1,
          "angle": 0,
          "clipped": false,
          "clipXOffset": 0,
          "clipYOffset": 0,
          "clipWidthFactor": 1,
          "clipHeightFactor": 1
        },
        "layer1": {
          "cx": 3625.3577262240406,
          "cy": 1278.0768629375334,
          "width": 3817.732981152329,
          "height": 2864.3405572876804,
          "opacity": 1,
          "angle": 0,
          "clipped": false,
          "clipXOffset": 0,
          "clipYOffset": 0,
          "clipWidthFactor": 1,
          "clipHeightFactor": 1
        },
        "__sozi_auto__": {
          "cx": 3625.3577262240406,
          "cy": 1278.0782379095826,
          "width": 3817.1585257061006,
          "height": 2863.909559090291,
          "opacity": 1,
          "angle": 0,
          "clipped": false,
          "clipXOffset": 0,
          "clipYOffset": 0,
          "clipWidthFactor": 1,
          "clipHeightFactor": 1
        }
      },
      "cameraOffsets": {
        "layer1": {
          "deltaX": -664.1066292447094,
          "deltaY": -241.7817796405916,
          "widthFactor": 1.62518771356043,
          "heightFactor": 2.220566756727177,
          "deltaAngle": 0
        }
      }
    },
    {
      "frameId": "frame1677",
      "title": "What are EELS and CL?",
      "timeoutMs": 0,
      "timeoutEnable": false,
      "transitionDurationMs": 1000,
      "showInFrameList": true,
      "showFrameNumber": true,
      "layerProperties": {
        "layer2": {
          "link": true,
          "referenceElementId": "",
          "outlineElementId": "",
          "outlineElementAuto": true,
          "transitionTimingFunction": "linear",
          "transitionRelativeZoom": 0,
          "transitionPathId": ""
        },
        "layer3": {
          "link": false,
          "referenceElementId": "",
          "outlineElementId": "text4066",
          "outlineElementAuto": true,
          "transitionTimingFunction": "linear",
          "transitionRelativeZoom": 0,
          "transitionPathId": ""
        },
        "layer1": {
          "link": false,
          "referenceElementId": "text4066",
          "outlineElementId": "text4066",
          "outlineElementAuto": true,
          "transitionTimingFunction": "linear",
          "transitionRelativeZoom": 0,
          "transitionPathId": ""
        },
        "__sozi_auto__": {
          "link": false,
          "referenceElementId": "",
          "outlineElementId": "text4066",
          "outlineElementAuto": true,
          "transitionTimingFunction": "linear",
          "transitionRelativeZoom": 0,
          "transitionPathId": ""
        }
      },
      "cameraStates": {
        "layer2": {
          "cx": 1785.5036080860511,
          "cy": 8648.459552366347,
          "width": 2848.422463284651,
          "height": 2137.0934075679825,
          "opacity": 1,
          "angle": 0,
          "clipped": false,
          "clipXOffset": 0,
          "clipYOffset": 0,
          "clipWidthFactor": 1,
          "clipHeightFactor": 1
        },
        "layer3": {
          "cx": 4569.7977078048,
          "cy": 2775.684719804081,
          "width": 2343.404209797081,
          "height": 1758.1920352676027,
          "opacity": 1,
          "angle": 0,
          "clipped": false,
          "clipXOffset": 0,
          "clipYOffset": 0,
          "clipWidthFactor": 1,
          "clipHeightFactor": 1
        },
        "layer1": {
          "cx": 4565.573140144753,
          "cy": 2780.064729908445,
          "width": 2354.0788143277023,
          "height": 1736.2078007865405,
          "opacity": 1,
          "angle": 0,
          "clipped": false,
          "clipXOffset": 0,
          "clipYOffset": 0,
          "clipWidthFactor": 1,
          "clipHeightFactor": 1
        },
        "__sozi_auto__": {
          "cx": 4569.7977078048,
          "cy": 2775.684719804081,
          "width": 2343.404209797081,
          "height": 1758.1920352676027,
          "opacity": 1,
          "angle": 0,
          "clipped": false,
          "clipXOffset": 0,
          "clipYOffset": 0,
          "clipWidthFactor": 1,
          "clipHeightFactor": 1
        }
      },
      "cameraOffsets": {
        "layer1": {
          "deltaX": 143.31483936350287,
          "deltaY": 403.20193693969486,
          "widthFactor": 1.2228411950915465,
          "heightFactor": 3.65653181008635,
          "deltaAngle": 0
        }
      }
    },
    {
      "frameId": "frame7509",
      "title": "EELS in a TEM",
      "timeoutMs": 0,
      "timeoutEnable": false,
      "transitionDurationMs": 1000,
      "showInFrameList": true,
      "showFrameNumber": true,
      "layerProperties": {
        "layer2": {
          "link": true,
          "referenceElementId": "",
          "outlineElementId": "",
          "outlineElementAuto": true,
          "transitionTimingFunction": "linear",
          "transitionRelativeZoom": 0,
          "transitionPathId": ""
        },
        "layer3": {
          "link": false,
          "referenceElementId": "",
          "outlineElementId": "image3777",
          "outlineElementAuto": true,
          "transitionTimingFunction": "linear",
          "transitionRelativeZoom": 0,
          "transitionPathId": ""
        },
        "layer1": {
          "link": false,
          "referenceElementId": "image3777",
          "outlineElementId": "image3777",
          "outlineElementAuto": true,
          "transitionTimingFunction": "linear",
          "transitionRelativeZoom": 0,
          "transitionPathId": ""
        },
        "__sozi_auto__": {
          "link": false,
          "referenceElementId": "",
          "outlineElementId": "image3777",
          "outlineElementAuto": true,
          "transitionTimingFunction": "linear",
          "transitionRelativeZoom": 0,
          "transitionPathId": ""
        }
      },
      "cameraStates": {
        "layer2": {
          "cx": 1785.5036080860511,
          "cy": 8648.459552366347,
          "width": 2848.422463284651,
          "height": 2137.0934075679825,
          "opacity": 1,
          "angle": 0,
          "clipped": false,
          "clipXOffset": 0,
          "clipYOffset": 0,
          "clipWidthFactor": 1,
          "clipHeightFactor": 1
        },
        "layer3": {
          "cx": 4562.131172767285,
          "cy": 4219.548818534015,
          "width": 2343.404209797081,
          "height": 1758.1920352676027,
          "opacity": 1,
          "angle": 0,
          "clipped": false,
          "clipXOffset": 0,
          "clipYOffset": 0,
          "clipWidthFactor": 1,
          "clipHeightFactor": 1
        },
        "layer1": {
          "cx": 4562.272150566528,
          "cy": 4219.990114146262,
          "width": 2343.756875609091,
          "height": 1758.4566307732334,
          "opacity": 1,
          "angle": 0,
          "clipped": false,
          "clipXOffset": 0,
          "clipYOffset": 0,
          "clipWidthFactor": 1,
          "clipHeightFactor": 1
        },
        "__sozi_auto__": {
          "cx": 4562.131172767285,
          "cy": 4219.548818534015,
          "width": 2343.404209797081,
          "height": 1758.1920352676027,
          "opacity": 1,
          "angle": 0,
          "clipped": false,
          "clipXOffset": 0,
          "clipYOffset": 0,
          "clipWidthFactor": 1,
          "clipHeightFactor": 1
        }
      },
      "cameraOffsets": {
        "layer1": {
          "deltaX": -29.65363068347233,
          "deltaY": -164.56847960373761,
          "widthFactor": 1.449286615287821,
          "heightFactor": 1.3645883312929785,
          "deltaAngle": 0
        }
      }
    },
    {
      "frameId": "frame5360",
      "title": "EELS Physical system 1,2",
      "timeoutMs": 0,
      "timeoutEnable": false,
      "transitionDurationMs": 1000,
      "showInFrameList": true,
      "showFrameNumber": true,
      "layerProperties": {
        "layer2": {
          "link": true,
          "referenceElementId": "",
          "outlineElementId": "",
          "outlineElementAuto": true,
          "transitionTimingFunction": "linear",
          "transitionRelativeZoom": 0,
          "transitionPathId": ""
        },
        "layer3": {
          "link": false,
          "referenceElementId": "",
          "outlineElementId": "text5058",
          "outlineElementAuto": true,
          "transitionTimingFunction": "linear",
          "transitionRelativeZoom": 0,
          "transitionPathId": ""
        },
        "layer1": {
          "link": false,
          "referenceElementId": "text5058",
          "outlineElementId": "text5058",
          "outlineElementAuto": true,
          "transitionTimingFunction": "linear",
          "transitionRelativeZoom": 0,
          "transitionPathId": ""
        },
        "__sozi_auto__": {
          "link": false,
          "referenceElementId": "",
          "outlineElementId": "text5058",
          "outlineElementAuto": true,
          "transitionTimingFunction": "linear",
          "transitionRelativeZoom": 0,
          "transitionPathId": ""
        }
      },
      "cameraStates": {
        "layer2": {
          "cx": 1785.5036080860511,
          "cy": 8648.459552366347,
          "width": 2848.422463284651,
          "height": 2137.0934075679825,
          "opacity": 1,
          "angle": 0,
          "clipped": false,
          "clipXOffset": 0,
          "clipYOffset": 0,
          "clipWidthFactor": 1,
          "clipHeightFactor": 1
        },
        "layer3": {
          "cx": 7243.739199627467,
          "cy": 4148.93812378165,
          "width": 2990.8435864489,
          "height": 2243.948077946394,
          "opacity": 1,
          "angle": 0,
          "clipped": false,
          "clipXOffset": 0,
          "clipYOffset": 0,
          "clipWidthFactor": 1,
          "clipHeightFactor": 1
        },
        "layer1": {
          "cx": 7251.898486622536,
          "cy": 4146.19057032591,
          "width": 2976.2001406884406,
          "height": 2232.7017434977056,
          "opacity": 1,
          "angle": 0,
          "clipped": false,
          "clipXOffset": 0,
          "clipYOffset": 0,
          "clipWidthFactor": 1,
          "clipHeightFactor": 1
        },
        "__sozi_auto__": {
          "cx": 7243.739199627467,
          "cy": 4148.93812378165,
          "width": 2990.8435864489,
          "height": 2243.948077946394,
          "opacity": 1,
          "angle": 0,
          "clipped": false,
          "clipXOffset": 0,
          "clipYOffset": 0,
          "clipWidthFactor": 1,
          "clipHeightFactor": 1
        }
      },
      "cameraOffsets": {
        "layer1": {
          "deltaX": 172.37114287253644,
          "deltaY": -766.1522031115901,
          "widthFactor": 2.5678543325250054,
          "heightFactor": 3.7529192958913673,
          "deltaAngle": 0
        }
      }
    },
    {
      "frameId": "frame5002",
      "title": "EELS Theoretical models",
      "timeoutMs": 0,
      "timeoutEnable": false,
      "transitionDurationMs": 1000,
      "showInFrameList": true,
      "showFrameNumber": true,
      "layerProperties": {
        "layer2": {
          "link": true,
          "referenceElementId": "",
          "outlineElementId": "",
          "outlineElementAuto": true,
          "transitionTimingFunction": "linear",
          "transitionRelativeZoom": 0,
          "transitionPathId": ""
        },
        "layer3": {
          "link": false,
          "referenceElementId": "",
          "outlineElementId": "text17821",
          "outlineElementAuto": true,
          "transitionTimingFunction": "linear",
          "transitionRelativeZoom": 0,
          "transitionPathId": ""
        },
        "layer1": {
          "link": false,
          "referenceElementId": "text17821",
          "outlineElementId": "text17821",
          "outlineElementAuto": true,
          "transitionTimingFunction": "linear",
          "transitionRelativeZoom": 0,
          "transitionPathId": ""
        },
        "__sozi_auto__": {
          "link": false,
          "referenceElementId": "",
          "outlineElementId": "text17821",
          "outlineElementAuto": true,
          "transitionTimingFunction": "linear",
          "transitionRelativeZoom": 0,
          "transitionPathId": ""
        }
      },
      "cameraStates": {
        "layer2": {
          "cx": 1785.5036080860511,
          "cy": 8648.459552366347,
          "width": 2848.422463284651,
          "height": 2137.0934075679825,
          "opacity": 1,
          "angle": 0,
          "clipped": false,
          "clipXOffset": 0,
          "clipYOffset": 0,
          "clipWidthFactor": 1,
          "clipHeightFactor": 1
        },
        "layer3": {
          "cx": 7911.180696160112,
          "cy": 3599.881760454676,
          "width": 4418.83813832054,
          "height": 3315.33330334191,
          "opacity": 1,
          "angle": 0,
          "clipped": false,
          "clipXOffset": 0,
          "clipYOffset": 0,
          "clipWidthFactor": 1,
          "clipHeightFactor": 1
        },
        "layer1": {
          "cx": 7907.0021815555665,
          "cy": 3596.531129584584,
          "width": 4465.648005078117,
          "height": 3350.7132656490744,
          "opacity": 1,
          "angle": 0,
          "clipped": false,
          "clipXOffset": 0,
          "clipYOffset": 0,
          "clipWidthFactor": 1,
          "clipHeightFactor": 1
        },
        "__sozi_auto__": {
          "cx": 7911.180696160112,
          "cy": 3599.881760454676,
          "width": 4418.83813832054,
          "height": 3315.33330334191,
          "opacity": 1,
          "angle": 0,
          "clipped": false,
          "clipXOffset": 0,
          "clipYOffset": 0,
          "clipWidthFactor": 1,
          "clipHeightFactor": 1
        }
      },
      "cameraOffsets": {
        "layer1": {
          "deltaX": -1253.0398106319335,
          "deltaY": 1323.746461615834,
          "widthFactor": 2.903613196586964,
          "heightFactor": 4.813092621850316,
          "deltaAngle": 0
        }
      }
    },
    {
      "frameId": "frame2599",
      "title": "CL",
      "timeoutMs": 0,
      "timeoutEnable": false,
      "transitionDurationMs": 1000,
      "showInFrameList": true,
      "showFrameNumber": true,
      "layerProperties": {
        "layer2": {
          "link": true,
          "referenceElementId": "",
          "outlineElementId": "",
          "outlineElementAuto": true,
          "transitionTimingFunction": "linear",
          "transitionRelativeZoom": 0,
          "transitionPathId": ""
        },
        "layer3": {
          "link": false,
          "referenceElementId": "",
          "outlineElementId": "image6404",
          "outlineElementAuto": true,
          "transitionTimingFunction": "linear",
          "transitionRelativeZoom": 0,
          "transitionPathId": ""
        },
        "layer1": {
          "link": false,
          "referenceElementId": "image6404",
          "outlineElementId": "image6404",
          "outlineElementAuto": true,
          "transitionTimingFunction": "linear",
          "transitionRelativeZoom": 0,
          "transitionPathId": ""
        },
        "__sozi_auto__": {
          "link": false,
          "referenceElementId": "",
          "outlineElementId": "image6404",
          "outlineElementAuto": true,
          "transitionTimingFunction": "linear",
          "transitionRelativeZoom": 0,
          "transitionPathId": ""
        }
      },
      "cameraStates": {
        "layer2": {
          "cx": 1785.5036080860511,
          "cy": 8648.459552366347,
          "width": 2848.422463284651,
          "height": 2137.0934075679825,
          "opacity": 1,
          "angle": 0,
          "clipped": false,
          "clipXOffset": 0,
          "clipYOffset": 0,
          "clipWidthFactor": 1,
          "clipHeightFactor": 1
        },
        "layer3": {
          "cx": 4837.012043324785,
          "cy": 6266.265694515717,
          "width": 2712.7832983663557,
          "height": 2035.327054826666,
          "opacity": 1,
          "angle": 0,
          "clipped": false,
          "clipXOffset": 0,
          "clipYOffset": 0,
          "clipWidthFactor": 1,
          "clipHeightFactor": 1
        },
        "layer1": {
          "cx": 4837.723114484135,
          "cy": 6269.5378659079015,
          "width": 2714.8317624977904,
          "height": 2036.8639613941982,
          "opacity": 1,
          "angle": 0,
          "clipped": false,
          "clipXOffset": 0,
          "clipYOffset": 0,
          "clipWidthFactor": 1,
          "clipHeightFactor": 1
        },
        "__sozi_auto__": {
          "cx": 4837.012043324785,
          "cy": 6266.265694515717,
          "width": 2712.7832983663557,
          "height": 2035.327054826666,
          "opacity": 1,
          "angle": 0,
          "clipped": false,
          "clipXOffset": 0,
          "clipYOffset": 0,
          "clipWidthFactor": 1,
          "clipHeightFactor": 1
        }
      },
      "cameraOffsets": {
        "layer1": {
          "deltaX": 203.1200871403853,
          "deltaY": 128.1150143454015,
          "widthFactor": 1.6033516442994185,
          "heightFactor": 2.102281368819038,
          "deltaAngle": 0
        }
      }
    },
    {
      "frameId": "frame2029",
      "title": "Goals 1,2",
      "timeoutMs": 0,
      "timeoutEnable": false,
      "transitionDurationMs": 1000,
      "showInFrameList": true,
      "showFrameNumber": true,
      "layerProperties": {
        "layer2": {
          "link": true,
          "referenceElementId": "",
          "outlineElementId": "",
          "outlineElementAuto": true,
          "transitionTimingFunction": "linear",
          "transitionRelativeZoom": 0,
          "transitionPathId": ""
        },
        "layer3": {
          "link": false,
          "referenceElementId": "",
          "outlineElementId": "rect11561",
          "outlineElementAuto": true,
          "transitionTimingFunction": "linear",
          "transitionRelativeZoom": 0,
          "transitionPathId": ""
        },
        "layer1": {
          "link": false,
          "referenceElementId": "rect11561",
          "outlineElementId": "rect11561",
          "outlineElementAuto": true,
          "transitionTimingFunction": "linear",
          "transitionRelativeZoom": 0,
          "transitionPathId": ""
        },
        "__sozi_auto__": {
          "link": false,
          "referenceElementId": "",
          "outlineElementId": "rect11561",
          "outlineElementAuto": true,
          "transitionTimingFunction": "linear",
          "transitionRelativeZoom": 0,
          "transitionPathId": ""
        }
      },
      "cameraStates": {
        "layer2": {
          "cx": 1785.5036080860511,
          "cy": 8648.459552366347,
          "width": 2848.422463284651,
          "height": 2137.0934075679825,
          "opacity": 1,
          "angle": 0,
          "clipped": false,
          "clipXOffset": 0,
          "clipYOffset": 0,
          "clipWidthFactor": 1,
          "clipHeightFactor": 1
        },
        "layer3": {
          "cx": 6163.931032352694,
          "cy": 5158.253875476215,
          "width": 5639.681643610343,
          "height": 4231.298768597509,
          "opacity": 1,
          "angle": 0,
          "clipped": false,
          "clipXOffset": 0,
          "clipYOffset": 0,
          "clipWidthFactor": 1,
          "clipHeightFactor": 1
        },
        "layer1": {
          "cx": 6257.0723029778765,
          "cy": 5160.689370208711,
          "width": 6030.428940445923,
          "height": 4234.493886969872,
          "opacity": 1,
          "angle": 0,
          "clipped": false,
          "clipXOffset": 0,
          "clipYOffset": 0,
          "clipWidthFactor": 1,
          "clipHeightFactor": 1
        },
        "__sozi_auto__": {
          "cx": 6163.931032352694,
          "cy": 5158.253875476215,
          "width": 5639.681643610343,
          "height": 4231.298768597509,
          "opacity": 1,
          "angle": 0,
          "clipped": false,
          "clipXOffset": 0,
          "clipYOffset": 0,
          "clipWidthFactor": 1,
          "clipHeightFactor": 1
        }
      },
      "cameraOffsets": {
        "layer1": {
          "deltaX": -1421.7001579596235,
          "deltaY": -1111.025473541289,
          "widthFactor": 2.1136180699987013,
          "heightFactor": 2.2402507089745707,
          "deltaAngle": 0
        }
      }
    },
    {
      "frameId": "frame9022",
      "title": "Goal 3",
      "timeoutMs": 0,
      "timeoutEnable": false,
      "transitionDurationMs": 1000,
      "showInFrameList": true,
      "showFrameNumber": true,
      "layerProperties": {
        "layer2": {
          "link": true,
          "referenceElementId": "",
          "outlineElementId": "",
          "outlineElementAuto": true,
          "transitionTimingFunction": "linear",
          "transitionRelativeZoom": 0,
          "transitionPathId": ""
        },
        "layer3": {
          "link": false,
          "referenceElementId": "",
          "outlineElementId": "text11563-3",
          "outlineElementAuto": true,
          "transitionTimingFunction": "linear",
          "transitionRelativeZoom": 0,
          "transitionPathId": ""
        },
        "layer1": {
          "link": false,
          "referenceElementId": "text11563-3",
          "outlineElementId": "text11563-3",
          "outlineElementAuto": true,
          "transitionTimingFunction": "linear",
          "transitionRelativeZoom": 0,
          "transitionPathId": ""
        },
        "__sozi_auto__": {
          "link": false,
          "referenceElementId": "",
          "outlineElementId": "text11563-3",
          "outlineElementAuto": true,
          "transitionTimingFunction": "linear",
          "transitionRelativeZoom": 0,
          "transitionPathId": ""
        }
      },
      "cameraStates": {
        "layer2": {
          "cx": 1785.5036080860511,
          "cy": 8648.459552366347,
          "width": 2848.422463284651,
          "height": 2137.0934075679825,
          "opacity": 1,
          "angle": 0,
          "clipped": false,
          "clipXOffset": 0,
          "clipYOffset": 0,
          "clipWidthFactor": 1,
          "clipHeightFactor": 1
        },
        "layer3": {
          "cx": 7456.634400882087,
          "cy": 7764.763227165114,
          "width": 2990.843586448914,
          "height": 2243.9480779464043,
          "opacity": 1,
          "angle": 0,
          "clipped": false,
          "clipXOffset": 0,
          "clipYOffset": 0,
          "clipWidthFactor": 1,
          "clipHeightFactor": 1
        },
        "layer1": {
          "cx": 7463.490904943464,
          "cy": 7767.649032458027,
          "width": 3047.0552194110674,
          "height": 2291.6973418736166,
          "opacity": 1,
          "angle": 0,
          "clipped": false,
          "clipXOffset": 0,
          "clipYOffset": 0,
          "clipWidthFactor": 1,
          "clipHeightFactor": 1
        },
        "__sozi_auto__": {
          "cx": 7456.634400882087,
          "cy": 7764.763227165114,
          "width": 2990.843586448914,
          "height": 2243.9480779464043,
          "opacity": 1,
          "angle": 0,
          "clipped": false,
          "clipXOffset": 0,
          "clipYOffset": 0,
          "clipWidthFactor": 1,
          "clipHeightFactor": 1
        }
      },
      "cameraOffsets": {
        "layer1": {
          "deltaX": 120.99139322471365,
          "deltaY": 14.85850511427725,
          "widthFactor": 1.3583482205970556,
          "heightFactor": 2.654451179556157,
          "deltaAngle": 0
        }
      }
    },
    {
      "frameId": "frame4872",
      "title": "Normalization",
      "timeoutMs": 0,
      "timeoutEnable": false,
      "transitionDurationMs": 1000,
      "showInFrameList": true,
      "showFrameNumber": true,
      "layerProperties": {
        "layer2": {
          "link": true,
          "referenceElementId": "",
          "outlineElementId": "",
          "outlineElementAuto": true,
          "transitionTimingFunction": "linear",
          "transitionRelativeZoom": 0,
          "transitionPathId": ""
        },
        "layer3": {
          "link": false,
          "referenceElementId": "",
          "outlineElementId": "text18917",
          "outlineElementAuto": true,
          "transitionTimingFunction": "linear",
          "transitionRelativeZoom": 0,
          "transitionPathId": ""
        },
        "layer1": {
          "link": false,
          "referenceElementId": "text18917",
          "outlineElementId": "text18917",
          "outlineElementAuto": true,
          "transitionTimingFunction": "linear",
          "transitionRelativeZoom": 0,
          "transitionPathId": ""
        },
        "__sozi_auto__": {
          "link": false,
          "referenceElementId": "",
          "outlineElementId": "text18917",
          "outlineElementAuto": true,
          "transitionTimingFunction": "linear",
          "transitionRelativeZoom": 0,
          "transitionPathId": ""
        }
      },
      "cameraStates": {
        "layer2": {
          "cx": 1785.5036080860511,
          "cy": 8648.459552366347,
          "width": 2848.422463284651,
          "height": 2137.0934075679825,
          "opacity": 1,
          "angle": 0,
          "clipped": false,
          "clipXOffset": 0,
          "clipYOffset": 0,
          "clipWidthFactor": 1,
          "clipHeightFactor": 1
        },
        "layer3": {
          "cx": 6595.978229733126,
          "cy": 8525.368772263571,
          "width": 801.0924270229848,
          "height": 601.0377206017596,
          "opacity": 1,
          "angle": 0,
          "clipped": false,
          "clipXOffset": 0,
          "clipYOffset": 0,
          "clipWidthFactor": 1,
          "clipHeightFactor": 1
        },
        "layer1": {
          "cx": 6592.8732546339415,
          "cy": 8524.743145134777,
          "width": 823.2350025098118,
          "height": 571.3004918279794,
          "opacity": 1,
          "angle": 0,
          "clipped": false,
          "clipXOffset": 0,
          "clipYOffset": 0,
          "clipWidthFactor": 1,
          "clipHeightFactor": 1
        },
        "__sozi_auto__": {
          "cx": 6595.978229733126,
          "cy": 8525.368772263571,
          "width": 801.0924270229848,
          "height": 601.0377206017596,
          "opacity": 1,
          "angle": 0,
          "clipped": false,
          "clipXOffset": 0,
          "clipYOffset": 0,
          "clipWidthFactor": 1,
          "clipHeightFactor": 1
        }
      },
      "cameraOffsets": {
        "layer1": {
          "deltaX": 62.77364525894154,
          "deltaY": -259.45314392772343,
          "widthFactor": 1.2791251822849434,
          "heightFactor": 8.114953841318185,
          "deltaAngle": 0
        }
      }
    },
    {
      "frameId": "frame3444",
      "title": "Deconvolution",
      "timeoutMs": 0,
      "timeoutEnable": false,
      "transitionDurationMs": 1000,
      "showInFrameList": true,
      "showFrameNumber": true,
      "layerProperties": {
        "layer2": {
          "link": true,
          "referenceElementId": "",
          "outlineElementId": "",
          "outlineElementAuto": true,
          "transitionTimingFunction": "linear",
          "transitionRelativeZoom": 0,
          "transitionPathId": ""
        },
        "layer3": {
          "link": false,
          "referenceElementId": "",
          "outlineElementId": "text14295",
          "outlineElementAuto": true,
          "transitionTimingFunction": "linear",
          "transitionRelativeZoom": 0,
          "transitionPathId": ""
        },
        "layer1": {
          "link": false,
          "referenceElementId": "text14295",
          "outlineElementId": "text14295",
          "outlineElementAuto": true,
          "transitionTimingFunction": "linear",
          "transitionRelativeZoom": 0,
          "transitionPathId": ""
        },
        "__sozi_auto__": {
          "link": false,
          "referenceElementId": "",
          "outlineElementId": "text14295",
          "outlineElementAuto": true,
          "transitionTimingFunction": "linear",
          "transitionRelativeZoom": 0,
          "transitionPathId": ""
        }
      },
      "cameraStates": {
        "layer2": {
          "cx": 1785.5036080860511,
          "cy": 8648.459552366347,
          "width": 2848.422463284651,
          "height": 2137.0934075679825,
          "opacity": 1,
          "angle": 0,
          "clipped": false,
          "clipXOffset": 0,
          "clipYOffset": 0,
          "clipWidthFactor": 1,
          "clipHeightFactor": 1
        },
        "layer3": {
          "cx": 7472.59349243346,
          "cy": 8522.005407111958,
          "width": 801.0924270229848,
          "height": 601.0377206017596,
          "opacity": 1,
          "angle": 0,
          "clipped": false,
          "clipXOffset": 0,
          "clipYOffset": 0,
          "clipWidthFactor": 1,
          "clipHeightFactor": 1
        },
        "layer1": {
          "cx": 7475.805065666567,
          "cy": 8505.36689793399,
          "width": 830.6700790993589,
          "height": 596.643248488356,
          "opacity": 1,
          "angle": 0,
          "clipped": false,
          "clipXOffset": 0,
          "clipYOffset": 0,
          "clipWidthFactor": 1,
          "clipHeightFactor": 1
        },
        "__sozi_auto__": {
          "cx": 7472.59349243346,
          "cy": 8522.005407111958,
          "width": 801.0924270229848,
          "height": 601.0377206017596,
          "opacity": 1,
          "angle": 0,
          "clipped": false,
          "clipXOffset": 0,
          "clipYOffset": 0,
          "clipWidthFactor": 1,
          "clipHeightFactor": 1
        }
      },
      "cameraOffsets": {
        "layer1": {
          "deltaX": 49.421276604067316,
          "deltaY": -66.6106411285109,
          "widthFactor": 1.2389170045170816,
          "heightFactor": 1.8243856510702174,
          "deltaAngle": 0
        }
      }
    },
    {
      "frameId": "frame5068",
      "title": "Background subtraction",
      "timeoutMs": 0,
      "timeoutEnable": false,
      "transitionDurationMs": 1000,
      "showInFrameList": true,
      "showFrameNumber": true,
      "layerProperties": {
        "layer2": {
          "link": true,
          "referenceElementId": "",
          "outlineElementId": "",
          "outlineElementAuto": true,
          "transitionTimingFunction": "linear",
          "transitionRelativeZoom": 0,
          "transitionPathId": ""
        },
        "layer3": {
          "link": false,
          "referenceElementId": "",
          "outlineElementId": "text18901-9",
          "outlineElementAuto": true,
          "transitionTimingFunction": "linear",
          "transitionRelativeZoom": 0,
          "transitionPathId": ""
        },
        "layer1": {
          "link": false,
          "referenceElementId": "text18901-9",
          "outlineElementId": "text18901-9",
          "outlineElementAuto": true,
          "transitionTimingFunction": "linear",
          "transitionRelativeZoom": 0,
          "transitionPathId": ""
        },
        "__sozi_auto__": {
          "link": false,
          "referenceElementId": "",
          "outlineElementId": "text18901-9",
          "outlineElementAuto": true,
          "transitionTimingFunction": "linear",
          "transitionRelativeZoom": 0,
          "transitionPathId": ""
        }
      },
      "cameraStates": {
        "layer2": {
          "cx": 1785.5036080860511,
          "cy": 8648.459552366347,
          "width": 2848.422463284651,
          "height": 2137.0934075679825,
          "opacity": 1,
          "angle": 0,
          "clipped": false,
          "clipXOffset": 0,
          "clipYOffset": 0,
          "clipWidthFactor": 1,
          "clipHeightFactor": 1
        },
        "layer3": {
          "cx": 8323.635193703154,
          "cy": 8527.562269621816,
          "width": 424.8364178905464,
          "height": 318.74313577829435,
          "opacity": 1,
          "angle": 0,
          "clipped": false,
          "clipXOffset": 0,
          "clipYOffset": 0,
          "clipWidthFactor": 1,
          "clipHeightFactor": 1
        },
        "layer1": {
          "cx": 8434.910501908804,
          "cy": 8528.150416511942,
          "width": 921.1090280146905,
          "height": 689.6653490708031,
          "opacity": 1,
          "angle": 0,
          "clipped": false,
          "clipXOffset": 0,
          "clipYOffset": 0,
          "clipWidthFactor": 1,
          "clipHeightFactor": 1
        },
        "__sozi_auto__": {
          "cx": 8323.635193703154,
          "cy": 8527.562269621816,
          "width": 424.8364178905464,
          "height": 318.74313577829435,
          "opacity": 1,
          "angle": 0,
          "clipped": false,
          "clipXOffset": 0,
          "clipYOffset": 0,
          "clipWidthFactor": 1,
          "clipHeightFactor": 1
        }
      },
      "cameraOffsets": {
        "layer1": {
          "deltaX": 3.0394081588037807,
          "deltaY": -229.12985692555776,
          "widthFactor": 1.0467935454840271,
          "heightFactor": 4.801686363681209,
          "deltaAngle": 0
        }
      }
    },
    {
      "frameId": "frame1888",
      "title": "DD, IM?",
      "timeoutMs": 0,
      "timeoutEnable": false,
      "transitionDurationMs": 1000,
      "showInFrameList": true,
      "showFrameNumber": true,
      "layerProperties": {
        "layer2": {
          "link": true,
          "referenceElementId": "",
          "outlineElementId": "",
          "outlineElementAuto": true,
          "transitionTimingFunction": "linear",
          "transitionRelativeZoom": 0,
          "transitionPathId": ""
        },
        "layer3": {
          "link": false,
          "referenceElementId": "",
          "outlineElementId": "text17847-5",
          "outlineElementAuto": true,
          "transitionTimingFunction": "linear",
          "transitionRelativeZoom": 0,
          "transitionPathId": ""
        },
        "layer1": {
          "link": false,
          "referenceElementId": "text17847-5",
          "outlineElementId": "text17847-5",
          "outlineElementAuto": true,
          "transitionTimingFunction": "linear",
          "transitionRelativeZoom": 0,
          "transitionPathId": ""
        },
        "__sozi_auto__": {
          "link": false,
          "referenceElementId": "",
          "outlineElementId": "text17847-5",
          "outlineElementAuto": true,
          "transitionTimingFunction": "linear",
          "transitionRelativeZoom": 0,
          "transitionPathId": ""
        }
      },
      "cameraStates": {
        "layer2": {
          "cx": 1785.5036080860511,
          "cy": 8648.459552366347,
          "width": 2848.422463284651,
          "height": 2137.0934075679825,
          "opacity": 1,
          "angle": 0,
          "clipped": false,
          "clipXOffset": 0,
          "clipYOffset": 0,
          "clipWidthFactor": 1,
          "clipHeightFactor": 1
        },
        "layer3": {
          "cx": 7917.4899648491855,
          "cy": 8836.596924156222,
          "width": 1242.7572856474683,
          "height": 932.4067748369228,
          "opacity": 1,
          "angle": 0,
          "clipped": false,
          "clipXOffset": 0,
          "clipYOffset": 0,
          "clipWidthFactor": 1,
          "clipHeightFactor": 1
        },
        "layer1": {
          "cx": 7551.1609276024,
          "cy": 9198.689461885822,
          "width": 2698.859588070313,
          "height": 2027.380626922271,
          "opacity": 1,
          "angle": 0,
          "clipped": false,
          "clipXOffset": 0,
          "clipYOffset": 0,
          "clipWidthFactor": 1,
          "clipHeightFactor": 1
        },
        "__sozi_auto__": {
          "cx": 7917.4899648491855,
          "cy": 8836.596924156222,
          "width": 1242.7572856474683,
          "height": 932.4067748369228,
          "opacity": 1,
          "angle": 0,
          "clipped": false,
          "clipXOffset": 0,
          "clipYOffset": 0,
          "clipWidthFactor": 1,
          "clipHeightFactor": 1
        }
      },
      "cameraOffsets": {
        "layer1": {
          "deltaX": 379.4299705711501,
          "deltaY": 14.798836885822311,
          "widthFactor": 1.6006005015034013,
          "heightFactor": 3.237012521953097,
          "deltaAngle": 0
        }
      }
    },
    {
      "frameId": "frame6472",
      "title": "Goal 4",
      "timeoutMs": 0,
      "timeoutEnable": false,
      "transitionDurationMs": 1000,
      "showInFrameList": true,
      "showFrameNumber": true,
      "layerProperties": {
        "layer2": {
          "link": true,
          "referenceElementId": "",
          "outlineElementId": "",
          "outlineElementAuto": true,
          "transitionTimingFunction": "linear",
          "transitionRelativeZoom": 0,
          "transitionPathId": ""
        },
        "layer3": {
          "link": false,
          "referenceElementId": "",
          "outlineElementId": "path4316-5",
          "outlineElementAuto": true,
          "transitionTimingFunction": "linear",
          "transitionRelativeZoom": 0,
          "transitionPathId": ""
        },
        "layer1": {
          "link": false,
          "referenceElementId": "path4316-5",
          "outlineElementId": "path4316-5",
          "outlineElementAuto": true,
          "transitionTimingFunction": "linear",
          "transitionRelativeZoom": 0,
          "transitionPathId": ""
        },
        "__sozi_auto__": {
          "link": false,
          "referenceElementId": "",
          "outlineElementId": "path4316-5",
          "outlineElementAuto": true,
          "transitionTimingFunction": "linear",
          "transitionRelativeZoom": 0,
          "transitionPathId": ""
        }
      },
      "cameraStates": {
        "layer2": {
          "cx": 1785.5036080860511,
          "cy": 8648.459552366347,
          "width": 2848.422463284651,
          "height": 2137.0934075679825,
          "opacity": 1,
          "angle": 0,
          "clipped": false,
          "clipXOffset": 0,
          "clipYOffset": 0,
          "clipWidthFactor": 1,
          "clipHeightFactor": 1
        },
        "layer3": {
          "cx": 9169.152870780785,
          "cy": 8342.077736153482,
          "width": 1073.5404691912047,
          "height": 805.448029229606,
          "opacity": 1,
          "angle": 0,
          "clipped": false,
          "clipXOffset": 0,
          "clipYOffset": 0,
          "clipWidthFactor": 1,
          "clipHeightFactor": 1
        },
        "layer1": {
          "cx": 10268.970546259088,
          "cy": 8125.280574257719,
          "width": 2331.4659005974736,
          "height": 1749.2350486489222,
          "opacity": 1,
          "angle": 0,
          "clipped": false,
          "clipXOffset": 0,
          "clipYOffset": 0,
          "clipWidthFactor": 1,
          "clipHeightFactor": 1
        },
        "__sozi_auto__": {
          "cx": 9169.152870780785,
          "cy": 8342.077736153482,
          "width": 1073.5404691912047,
          "height": 805.448029229606,
          "opacity": 1,
          "angle": 0,
          "clipped": false,
          "clipXOffset": 0,
          "clipYOffset": 0,
          "clipWidthFactor": 1,
          "clipHeightFactor": 1
        }
      },
      "cameraOffsets": {
        "layer1": {
          "deltaX": 382.0545306340882,
          "deltaY": -322.8258710547807,
          "widthFactor": 1.8643337702813523,
          "heightFactor": 2.5473234152139668,
          "deltaAngle": 0
        }
      }
    },
    {
      "frameId": "frame1616",
      "title": "Data Constraints",
      "timeoutMs": 0,
      "timeoutEnable": false,
      "transitionDurationMs": 1000,
      "showInFrameList": true,
      "showFrameNumber": true,
      "layerProperties": {
        "layer2": {
          "link": true,
          "referenceElementId": "",
          "outlineElementId": "",
          "outlineElementAuto": true,
          "transitionTimingFunction": "linear",
          "transitionRelativeZoom": 0,
          "transitionPathId": ""
        },
        "layer3": {
          "link": false,
          "referenceElementId": "",
          "outlineElementId": "text19100",
          "outlineElementAuto": true,
          "transitionTimingFunction": "linear",
          "transitionRelativeZoom": 0,
          "transitionPathId": ""
        },
        "layer1": {
          "link": false,
          "referenceElementId": "text19100",
          "outlineElementId": "text19100",
          "outlineElementAuto": true,
          "transitionTimingFunction": "linear",
          "transitionRelativeZoom": 0,
          "transitionPathId": ""
        },
        "__sozi_auto__": {
          "link": false,
          "referenceElementId": "",
          "outlineElementId": "text19100",
          "outlineElementAuto": true,
          "transitionTimingFunction": "linear",
          "transitionRelativeZoom": 0,
          "transitionPathId": ""
        }
      },
      "cameraStates": {
        "layer2": {
          "cx": 1785.5036080860511,
          "cy": 8648.459552366347,
          "width": 2848.422463284651,
          "height": 2137.0934075679825,
          "opacity": 1,
          "angle": 0,
          "clipped": false,
          "clipXOffset": 0,
          "clipYOffset": 0,
          "clipWidthFactor": 1,
          "clipHeightFactor": 1
        },
        "layer3": {
          "cx": 8927.08999219091,
          "cy": 9062.253848495411,
          "width": 659.060722248846,
          "height": 494.47522018234025,
          "opacity": 1,
          "angle": 0,
          "clipped": false,
          "clipXOffset": 0,
          "clipYOffset": 0,
          "clipWidthFactor": 1,
          "clipHeightFactor": 1
        },
        "layer1": {
          "cx": 9743.394500579856,
          "cy": 9688.794738973254,
          "width": 1431.6184072575784,
          "height": 1073.6276315387122,
          "opacity": 1,
          "angle": 0,
          "clipped": false,
          "clipXOffset": 0,
          "clipYOffset": 0,
          "clipWidthFactor": 1,
          "clipHeightFactor": 1
        },
        "__sozi_auto__": {
          "cx": 8927.08999219091,
          "cy": 9062.253848495411,
          "width": 659.060722248846,
          "height": 494.47522018234025,
          "opacity": 1,
          "angle": 0,
          "clipped": false,
          "clipXOffset": 0,
          "clipYOffset": 0,
          "clipWidthFactor": 1,
          "clipHeightFactor": 1
        }
      },
      "cameraOffsets": {
        "layer1": {
          "deltaX": 62.32125839235596,
          "deltaY": 82.07598897325443,
          "widthFactor": 1.1993203136798598,
          "heightFactor": 2.0120439612788092,
          "deltaAngle": 0
        }
      }
    },
    {
      "frameId": "frame1416",
      "title": "Data Constraints",
      "timeoutMs": 0,
      "timeoutEnable": false,
      "transitionDurationMs": 1000,
      "showInFrameList": true,
      "showFrameNumber": true,
      "layerProperties": {
        "layer2": {
          "link": true,
          "referenceElementId": "",
          "outlineElementId": "",
          "outlineElementAuto": true,
          "transitionTimingFunction": "linear",
          "transitionRelativeZoom": 0,
          "transitionPathId": ""
        },
        "layer3": {
          "link": false,
          "referenceElementId": "",
          "outlineElementId": "text19265",
          "outlineElementAuto": true,
          "transitionTimingFunction": "linear",
          "transitionRelativeZoom": 0,
          "transitionPathId": ""
        },
        "layer1": {
          "link": false,
          "referenceElementId": "text19265",
          "outlineElementId": "text19265",
          "outlineElementAuto": true,
          "transitionTimingFunction": "linear",
          "transitionRelativeZoom": 0,
          "transitionPathId": ""
        },
        "__sozi_auto__": {
          "link": false,
          "referenceElementId": "",
          "outlineElementId": "text19265",
          "outlineElementAuto": true,
          "transitionTimingFunction": "linear",
          "transitionRelativeZoom": 0,
          "transitionPathId": ""
        }
      },
      "cameraStates": {
        "layer2": {
          "cx": 1785.5036080860511,
          "cy": 8648.459552366347,
          "width": 2848.422463284651,
          "height": 2137.0934075679825,
          "opacity": 1,
          "angle": 0,
          "clipped": false,
          "clipXOffset": 0,
          "clipYOffset": 0,
          "clipWidthFactor": 1,
          "clipHeightFactor": 1
        },
        "layer3": {
          "cx": 9639.426992688792,
          "cy": 9043.122366762167,
          "width": 627.6768783322342,
          "height": 470.9287811260383,
          "opacity": 1,
          "angle": 0,
          "clipped": false,
          "clipXOffset": 0,
          "clipYOffset": 0,
          "clipWidthFactor": 1,
          "clipHeightFactor": 1
        },
        "layer1": {
          "cx": 11290.708001571644,
          "cy": 9647.206150313392,
          "width": 1362.3313494644474,
          "height": 1022.4686177411348,
          "opacity": 1,
          "angle": 0,
          "clipped": false,
          "clipXOffset": 0,
          "clipYOffset": 0,
          "clipWidthFactor": 1,
          "clipHeightFactor": 1
        },
        "__sozi_auto__": {
          "cx": 9639.426992688792,
          "cy": 9043.122366762167,
          "width": 627.6768783322342,
          "height": 470.9287811260383,
          "opacity": 1,
          "angle": 0,
          "clipped": false,
          "clipXOffset": 0,
          "clipYOffset": 0,
          "clipWidthFactor": 1,
          "clipHeightFactor": 1
        }
      },
      "cameraOffsets": {
        "layer1": {
          "deltaX": 186.17089219664376,
          "deltaY": 15.454197188391845,
          "widthFactor": 1.4695502708986028,
          "heightFactor": 1.8680362578403646,
          "deltaAngle": 0
        }
      }
    }
  ],
  "elementsToHide": [],
  "selectedFrames": [
    "frame2346"
  ],
  "selectedLayers": [
    "layer3",
    "layer1",
    "__sozi_auto__"
  ],
  "editableLayers": [
    "layer2"
  ]
}